proj_template/__init__.py
proj_template/__main__.py
proj_template/proj_template.py
proj_template/templates/_gitignore.in
proj_template/templates/_init.py.in
proj_template/templates/_main.py.in
proj_template/templates/_setup.cfg.in
proj_template/templates/_setup.py.in
proj_template/templates/licenses/BSD-3-Clause.in
proj_template/templates/licenses/MIT.in
proj_template/templates/licenses/licenses.yml
proj_template-0.2.1.dist-info/COPYING
proj_template-0.2.1.dist-info/METADATA
proj_template-0.2.1.dist-info/WHEEL
proj_template-0.2.1.dist-info/entry_points.txt
proj_template-0.2.1.dist-info/top_level.txt
proj_template-0.2.1.dist-info/RECORD
